README.md
setup.py
single_cell_detect/__init__.py
single_cell_detect/single_cell_detect.py
single_cell_detect/utils.py
single_cell_detect.egg-info/PKG-INFO
single_cell_detect.egg-info/SOURCES.txt
single_cell_detect.egg-info/dependency_links.txt
single_cell_detect.egg-info/not-zip-safe
single_cell_detect.egg-info/top_level.txt