Metadata-Version: 1.0
Name: single-cell-detect
Version: 0.0.4
Summary: Package for detecting cell boundaries
Home-page: https://github.com/sofroniewn/SingleCellDetect
Author: Nicholas Sofroniew
Author-email: UNKNOWN
License: MIT
Platform: UNKNOWN
